Workbook

Sheet Dashboard
A1: PR.2 ANALYZER — SALES PERFORMANCE DASHBOARD
A3: Total Sales | C3: Total Profit | E3: Total Orders | G3: Average Discount | I3: Top Customer
A4: =SUM('Sales Data'!$J$2:$J$82) -> 120894.01 | C4: =SUM('Sales Data'!$K$2:$K$82) -> 49077.962 | E4: =COUNT('Sales Data'!$J$2:$J$82) -> 81 | G4: =AVERAGE('Sales Data'!$I$2:$I$82) -> 0.096296296 | I4: ='High-Value Customers'!B4 -> Sanjay Desai
A6: KEY INSIGHTS
A7: ="Top performing customer: "&'High-Value Customers'!B4&" with total purchases of "&TEXT('High-Value Customers'!C4,"$#,##0") -> Top performing customer: Sanjay Desai with total purchases of $14,426
A8: ="Best month for sales: "&INDEX('Monthly Growth'!A4:A9,MATCH(MAX('Monthly Growth'!B4:B9),'Monthly Growth'!B4:B9,0))&" with "&TEXT(MAX('Monthly Growth'!B4:B9),"$#,##0")&" in sales." -> Best month for sales: May-26 with $26,702 in sales.
A9: ="Strongest region: "&INDEX('Pivot Summary'!A5:A8,MATCH(MAX('Pivot Summary'!F5:F8),'Pivot Summary'!F5:F8,0))&" with "&TEXT(MAX('Pivot Summary'!F5:F8),"$#,##0")&" in total sales." -> Strongest region: South with $53,850 in total sales.
A10: ="Sales-Profit correlation (R): "&TEXT('Regression Analysis'!B5,"0.00")&" — Profit tends to rise with Sales." -> Sales-Profit correlation (R): 0.99 — Profit tends to rise with Sales.

Sheet Sales Data
A1: OrderID | B1: CustomerName | C1: Region | D1: Product | E1: OrderDate | F1: Quantity | G1: UnitPrice | H1: UnitCost | I1: Discount | J1: Sales | K1: Profit | L1: MonthLabel | M1: Timestamp | O1: Note: Timestamp column uses =NOW() and updates every time the workbook recalculates.
A2: 1001 | B2: Arjun Nair | C2: West | D2: Product B | E2: 2026-01-15 | F2: 14 | G2: 229.48 | H2: 134.66 | I2: 0.05 | J2: =F2*G2*(1-I2) -> 3052.084 | K2: =J2-(F2*H2*(1-I2)) -> 1261.106 | L2: =TEXT(E2,"mmm-yy") -> Jan-26 | M2: =NOW() -> 46275.438
A3: 1002 | B3: Divya Reddy | C3: North | D3: Product C | E3: 2026-01-11 | F3: 6 | G3: 100.25 | H3: 54.19 | I3: 0.15 | J3: =F3*G3*(1-I3) -> 511.275 | K3: =J3-(F3*H3*(1-I3)) -> 234.906 | L3: =TEXT(E3,"mmm-yy") -> Jan-26 | M3: =NOW() -> 46275.438
A4: 1003 | B4: Vikram Singh | C4: South | D4: Product B | E4: 2026-01-13 | F4: 4 | G4: 215.16 | H4: 135.48 | I4: 0 | J4: =F4*G4*(1-I4) -> 860.64 | K4: =J4-(F4*H4*(1-I4)) -> 318.72 | L4: =TEXT(E4,"mmm-yy") -> Jan-26 | M4: =NOW() -> 46275.438
A5: 1004 | B5: Priya Patel | C5: North | D5: Product C | E5: 2026-01-18 | F5: 2 | G5: 100.72 | H5: 57.59 | I5: 0.15 | J5: =F5*G5*(1-I5) -> 171.224 | K5: =J5-(F5*H5*(1-I5)) -> 73.321 | L5: =TEXT(E5,"mmm-yy") -> Jan-26 | M5: =NOW() -> 46275.438
A6: 1005 | B6: Priya Patel | C6: North | D6: Product D | E6: 2026-01-07 | F6: 12 | G6: 249.66 | H6: 152.77 | I6: 0.2 | J6: =F6*G6*(1-I6) -> 2396.736 | K6: =J6-(F6*H6*(1-I6)) -> 930.144 | L6: =TEXT(E6,"mmm-yy") -> Jan-26 | M6: =NOW() -> 46275.438
A7: 1006 | B7: Pooja Joshi | C7: North | D7: Product A | E7: 2026-01-28 | F7: 10 | G7: 143.39 | H7: 87.55 | I7: 0 | J7: =F7*G7*(1-I7) -> 1433.9 | K7: =J7-(F7*H7*(1-I7)) -> 558.4 | L7: =TEXT(E7,"mmm-yy") -> Jan-26 | M7: =NOW() -> 46275.438
A8: 1007 | B8: Sneha Iyer | C8: South | D8: Product A | E8: 2026-01-12 | F8: 12 | G8: 149.91 | H8: 89.58 | I8: 0.05 | J8: =F8*G8*(1-I8) -> 1708.974 | K8: =J8-(F8*H8*(1-I8)) -> 687.762 | L8: =TEXT(E8,"mmm-yy") -> Jan-26 | M8: =NOW() -> 46275.438
A9: 1008 | B9: Anjali Gupta | C9: South | D9: Product B | E9: 2026-01-21 | F9: 3 | G9: 228.17 | H9: 134.66 | I9: 0.2 | J9: =F9*G9*(1-I9) -> 547.608 | K9: =J9-(F9*H9*(1-I9)) -> 224.424 | L9: =TEXT(E9,"mmm-yy") -> Jan-26 | M9: =NOW() -> 46275.438
A10: 1009 | B10: Rohan Mehta | C10: East | D10: Product B | E10: 2026-01-22 | F10: 18 | G10: 213.67 | H10: 130.41 | I10: 0.05 | J10: =F10*G10*(1-I10) -> 3653.757 | K10: =J10-(F10*H10*(1-I10)) -> 1423.746 | L10: =TEXT(E10,"mmm-yy") -> Jan-26 | M10: =NOW() -> 46275.438
A11: 1010 | B11: Anjali Gupta | C11: South | D11: Product A | E11: 2026-01-09 | F11: 11 | G11: 146.97 | H11: 85.79 | I11: 0.15 | J11: =F11*G11*(1-I11) -> 1374.1695 | K11: =J11-(F11*H11*(1-I11)) -> 572.033 | L11: =TEXT(E11,"mmm-yy") -> Jan-26 | M11: =NOW() -> 46275.438
A12: 1011 | B12: Priya Patel | C12: North | D12: Product B | E12: 2026-01-21 | F12: 11 | G12: 235.12 | H12: 132.89 | I12: 0.05 | J12: =F12*G12*(1-I12) -> 2457.004 | K12: =J12-(F12*H12*(1-I12)) -> 1068.3035 | L12: =TEXT(E12,"mmm-yy") -> Jan-26 | M12: =NOW() -> 46275.438
A13: 1012 | B13: Neha Verma | C13: North | D13: Product D | E13: 2026-02-05 | F13: 5 | G13: 276.9 | H13: 158.23 | I13: 0.1 | J13: =F13*G13*(1-I13) -> 1246.05 | K13: =J13-(F13*H13*(1-I13)) -> 534.015 | L13: =TEXT(E13,"mmm-yy") -> Feb-26 | M13: =NOW() -> 46275.438
... A82: 1081 | B82: Pooja Joshi | C82: North | D82: Product B | E82: 2026-06-13 | F82: 16 | G82: 222.96 | H82: 129 | I82: 0 | J82: =F82*G82*(1-I82) -> 3567.36 | K82: =J82-(F82*H82*(1-I82)) -> 1503.36 | L82: =TEXT(E82,"mmm-yy") -> Jun-26 | M82: =NOW() -> 46275.438

Sheet Customer Summary
A1: TOP CUSTOMERS BY TOTAL PURCHASE
A3: Customer Name | B3: Total Purchase (Sales) | C3: Total Profit
A4: Amit Sharma | B4: =SUMIF('Sales Data'!$B$2:$B$82,A4,'Sales Data'!$J$2:$J$82) -> 5741.271 | C4: =SUMIF('Sales Data'!$B$2:$B$82,A4,'Sales Data'!$K$2:$K$82) -> 2180.106
A5: Priya Patel | B5: =SUMIF('Sales Data'!$B$2:$B$82,A5,'Sales Data'!$J$2:$J$82) -> 8769.024 | C5: =SUMIF('Sales Data'!$B$2:$B$82,A5,'Sales Data'!$K$2:$K$82) -> 3571.4885
A6: Rohan Mehta | B6: =SUMIF('Sales Data'!$B$2:$B$82,A6,'Sales Data'!$J$2:$J$82) -> 13221.466 | C6: =SUMIF('Sales Data'!$B$2:$B$82,A6,'Sales Data'!$K$2:$K$82) -> 5230.402
A7: Sneha Iyer | B7: =SUMIF('Sales Data'!$B$2:$B$82,A7,'Sales Data'!$J$2:$J$82) -> 5355.9205 | C7: =SUMIF('Sales Data'!$B$2:$B$82,A7,'Sales Data'!$K$2:$K$82) -> 2176.7695
A8: Vikram Singh | B8: =SUMIF('Sales Data'!$B$2:$B$82,A8,'Sales Data'!$J$2:$J$82) -> 13062.964 | C8: =SUMIF('Sales Data'!$B$2:$B$82,A8,'Sales Data'!$K$2:$K$82) -> 5235.526
A9: Anjali Gupta | B9: =SUMIF('Sales Data'!$B$2:$B$82,A9,'Sales Data'!$J$2:$J$82) -> 8971.1275 | C9: =SUMIF('Sales Data'!$B$2:$B$82,A9,'Sales Data'!$K$2:$K$82) -> 3638.807
A10: Karan Malhotra | B10: =SUMIF('Sales Data'!$B$2:$B$82,A10,'Sales Data'!$J$2:$J$82) -> 5937.902 | C10: =SUMIF('Sales Data'!$B$2:$B$82,A10,'Sales Data'!$K$2:$K$82) -> 2355.4005
A11: Neha Verma | B11: =SUMIF('Sales Data'!$B$2:$B$82,A11,'Sales Data'!$J$2:$J$82) -> 7754.134 | C11: =SUMIF('Sales Data'!$B$2:$B$82,A11,'Sales Data'!$K$2:$K$82) -> 3267.2595
A12: Arjun Nair | B12: =SUMIF('Sales Data'!$B$2:$B$82,A12,'Sales Data'!$J$2:$J$82) -> 10858.26 | C12: =SUMIF('Sales Data'!$B$2:$B$82,A12,'Sales Data'!$K$2:$K$82) -> 4526.782
A13: Divya Reddy | B13: =SUMIF('Sales Data'!$B$2:$B$82,A13,'Sales Data'!$J$2:$J$82) -> 511.275 | C13: =SUMIF('Sales Data'!$B$2:$B$82,A13,'Sales Data'!$K$2:$K$82) -> 234.906
A14: Rahul Kapoor | B14: =SUMIF('Sales Data'!$B$2:$B$82,A14,'Sales Data'!$J$2:$J$82) -> 4252.692 | C14: =SUMIF('Sales Data'!$B$2:$B$82,A14,'Sales Data'!$K$2:$K$82) -> 1692.178
A15: Pooja Joshi | B15: =SUMIF('Sales Data'!$B$2:$B$82,A15,'Sales Data'!$J$2:$J$82) -> 7689.26 | C15: =SUMIF('Sales Data'!$B$2:$B$82,A15,'Sales Data'!$K$2:$K$82) -> 3059.138
... A18: Aditya Bose | B18: =SUMIF('Sales Data'!$B$2:$B$82,A18,'Sales Data'!$J$2:$J$82) -> 2308.97 | C18: =SUMIF('Sales Data'!$B$2:$B$82,A18,'Sales Data'!$K$2:$K$82) -> 950.28

Sheet WHAT-IF Analysis
A1: WHAT-IF ANALYSIS: DISCOUNT IMPACT ON TOTAL PROFIT
A3: Total Quantity x Unit Price (Base Sales) | B3: =SUMPRODUCT('Sales Data'!$F$2:$F$82,'Sales Data'!$G$2:$G$82) -> 134438.21
A4: Total Quantity x Unit Cost (Base Cost) | B4: =SUMPRODUCT('Sales Data'!$F$2:$F$82,'Sales Data'!$H$2:$H$82) -> 79796.57
A6: Discount Lever (change this cell): | B6: 0.1
A7: Resulting Total Profit | B7: =B3*(1-B6)-B4 -> 41197.819
A9: Sensitivity Table: Discount Rate vs Total Profit
A10: Discount % | B10: Total Profit
A11: 0 | B11: =$B$3*(1-A11)-$B$4 -> 54641.64
A12: 0.05 | B12: =$B$3*(1-A12)-$B$4 -> 47919.729
A13: 0.1 | B13: =$B$3*(1-A13)-$B$4 -> 41197.819
A14: 0.15 | B14: =$B$3*(1-A14)-$B$4 -> 34475.908
A15: 0.2 | B15: =$B$3*(1-A15)-$B$4 -> 27753.998
A16: 0.25 | B16: =$B$3*(1-A16)-$B$4 -> 21032.087
A17: 0.3 | B17: =$B$3*(1-A17)-$B$4 -> 14310.177

Sheet Regression Analysis
A1: LINEAR REGRESSION: PROFIT vs SALES
A2: (Equivalent to Data Analysis Toolpak > Regression, Y = Profit, X = Sales)
A4: Regression Statistics
A5: Multiple R | B5: =CORREL('Sales Data'!$K$2:$K$82,'Sales Data'!$J$2:$J$82) -> 0.99242086
A6: R Square | B6: =RSQ('Sales Data'!$K$2:$K$82,'Sales Data'!$J$2:$J$82) -> 0.98489916
A7: Adjusted R Square | B7: =1-(1-B6)*(COUNT('Sales Data'!$J$2:$J$82)-1)/(COUNT('Sales Data'!$J$2:$J$82)-2) -> 0.98470801
A8: Standard Error | B8: =STEYX('Sales Data'!$K$2:$K$82,'Sales Data'!$J$2:$J$82) -> 50.640958
A9: Observations | B9: =COUNT('Sales Data'!$J$2:$J$82) -> 81
A11: Coefficients
B12: Coefficient
A13: Intercept | B13: =INTERCEPT('Sales Data'!$K$2:$K$82,'Sales Data'!$J$2:$J$82) -> 1.4638327
A14: Sales (Slope) | B14: =SLOPE('Sales Data'!$K$2:$K$82,'Sales Data'!$J$2:$J$82) -> 0.40497782

Sheet Descriptive Statistics
A1: DESCRIPTIVE STATISTICS
A3: Measure | B3: Sales | C3: Profit
A4: Mean | B4: =AVERAGE('Sales Data'!$J$2:$J$82) -> 1492.5186 | C4: =AVERAGE('Sales Data'!$K$2:$K$82) -> 605.90077
A5: Standard Error | B5: =STDEV('Sales Data'!$J$2:$J$82)/SQRT(COUNT('Sales Data'!$J$2:$J$82)) -> 111.5044 | C5: =STDEV('Sales Data'!$K$2:$K$82)/SQRT(COUNT('Sales Data'!$K$2:$K$82)) -> 45.501672
A6: Median | B6: =MEDIAN('Sales Data'!$J$2:$J$82) -> 1298.7 | C6: =MEDIAN('Sales Data'!$K$2:$K$82) -> 526.44
A7: Mode | B7: =IFERROR(MODE('Sales Data'!$J$2:$J$82),"No mode") -> No mode | C7: =IFERROR(MODE('Sales Data'!$K$2:$K$82),"No mode") -> No mode
A8: Standard Deviation | B8: =STDEV('Sales Data'!$J$2:$J$82) -> 1003.5396 | C8: =STDEV('Sales Data'!$K$2:$K$82) -> 409.51505
A9: Sample Variance | B9: =VAR('Sales Data'!$J$2:$J$82) -> 1007091.7 | C9: =VAR('Sales Data'!$K$2:$K$82) -> 167702.58
A10: Kurtosis | B10: =KURT('Sales Data'!$J$2:$J$82) -> 0.038253257 | C10: =KURT('Sales Data'!$K$2:$K$82) -> -0.25538927
A11: Skewness | B11: =SKEW('Sales Data'!$J$2:$J$82) -> 0.86392192 | C11: =SKEW('Sales Data'!$K$2:$K$82) -> 0.79250134
A12: Range | B12: =MAX('Sales Data'!$J$2:$J$82)-MIN('Sales Data'!$J$2:$J$82) -> 4268.652 | C12: =MAX('Sales Data'!$K$2:$K$82)-MIN('Sales Data'!$K$2:$K$82) -> 1642.874
A13: Minimum | B13: =MIN('Sales Data'!$J$2:$J$82) -> 143.49 | C13: =MIN('Sales Data'!$K$2:$K$82) -> 49
A14: Maximum | B14: =MAX('Sales Data'!$J$2:$J$82) -> 4412.142 | C14: =MAX('Sales Data'!$K$2:$K$82) -> 1691.874
A15: Sum | B15: =SUM('Sales Data'!$J$2:$J$82) -> 120894.01 | C15: =SUM('Sales Data'!$K$2:$K$82) -> 49077.962
A16: Count | B16: =COUNT('Sales Data'!$J$2:$J$82) -> 81 | C16: =COUNT('Sales Data'!$K$2:$K$82) -> 81

Sheet Monthly Growth
A1: MONTHLY SALES GROWTH
A3: Month | B3: Total Sales | C3: Growth vs Prior Month
A4: Jan-26 | B4: =SUMIF('Sales Data'!$L$2:$L$82,A4,'Sales Data'!$J$2:$J$82) -> 18167.372 | C4: n/a (base month)
A5: Feb-26 | B5: =SUMIF('Sales Data'!$L$2:$L$82,A5,'Sales Data'!$J$2:$J$82) -> 20616.168 | C5: =(B5-B4)/B4 -> 0.13479091
A6: Mar-26 | B6: =SUMIF('Sales Data'!$L$2:$L$82,A6,'Sales Data'!$J$2:$J$82) -> 14586.574 | C6: =(B6-B5)/B5 -> -0.29246919
A7: Apr-26 | B7: =SUMIF('Sales Data'!$L$2:$L$82,A7,'Sales Data'!$J$2:$J$82) -> 17507.098 | C7: =(B7-B6)/B6 -> 0.20021998
A8: May-26 | B8: =SUMIF('Sales Data'!$L$2:$L$82,A8,'Sales Data'!$J$2:$J$82) -> 26702.181 | C8: =(B8-B7)/B7 -> 0.52522033
A9: Jun-26 | B9: =SUMIF('Sales Data'!$L$2:$L$82,A9,'Sales Data'!$J$2:$J$82) -> 23314.616 | C9: =(B9-B8)/B8 -> -0.12686475

Sheet High-Value Customers
A1: HIGH-VALUE CUSTOMERS (TOP 10 BY TOTAL PURCHASE)
A3: Rank | B3: Customer Name | C3: Total Purchase | D3: Region
A4: 1 | B4: =INDEX('Customer Summary'!$A$4:$A$18,MATCH(C4,'Customer Summary'!$B$4:$B$18,0)) -> Sanjay Desai | C4: =LARGE('Customer Summary'!$B$4:$B$18,A4) -> 14426.24 | D4: =INDEX('Sales Data'!$C$2:$C$82,MATCH(B4,'Sales Data'!$B$2:$B$82,0)) -> South
A5: 2 | B5: =INDEX('Customer Summary'!$A$4:$A$18,MATCH(C5,'Customer Summary'!$B$4:$B$18,0)) -> Rohan Mehta | C5: =LARGE('Customer Summary'!$B$4:$B$18,A5) -> 13221.466 | D5: =INDEX('Sales Data'!$C$2:$C$82,MATCH(B5,'Sales Data'!$B$2:$B$82,0)) -> East
A6: 3 | B6: =INDEX('Customer Summary'!$A$4:$A$18,MATCH(C6,'Customer Summary'!$B$4:$B$18,0)) -> Vikram Singh | C6: =LARGE('Customer Summary'!$B$4:$B$18,A6) -> 13062.964 | D6: =INDEX('Sales Data'!$C$2:$C$82,MATCH(B6,'Sales Data'!$B$2:$B$82,0)) -> South
A7: 4 | B7: =INDEX('Customer Summary'!$A$4:$A$18,MATCH(C7,'Customer Summary'!$B$4:$B$18,0)) -> Meera Rao | C7: =LARGE('Customer Summary'!$B$4:$B$18,A7) -> 12033.5 | D7: =INDEX('Sales Data'!$C$2:$C$82,MATCH(B7,'Sales Data'!$B$2:$B$82,0)) -> South
A8: 5 | B8: =INDEX('Customer Summary'!$A$4:$A$18,MATCH(C8,'Customer Summary'!$B$4:$B$18,0)) -> Arjun Nair | C8: =LARGE('Customer Summary'!$B$4:$B$18,A8) -> 10858.26 | D8: =INDEX('Sales Data'!$C$2:$C$82,MATCH(B8,'Sales Data'!$B$2:$B$82,0)) -> West
A9: 6 | B9: =INDEX('Customer Summary'!$A$4:$A$18,MATCH(C9,'Customer Summary'!$B$4:$B$18,0)) -> Anjali Gupta | C9: =LARGE('Customer Summary'!$B$4:$B$18,A9) -> 8971.1275 | D9: =INDEX('Sales Data'!$C$2:$C$82,MATCH(B9,'Sales Data'!$B$2:$B$82,0)) -> South
A10: 7 | B10: =INDEX('Customer Summary'!$A$4:$A$18,MATCH(C10,'Customer Summary'!$B$4:$B$18,0)) -> Priya Patel | C10: =LARGE('Customer Summary'!$B$4:$B$18,A10) -> 8769.024 | D10: =INDEX('Sales Data'!$C$2:$C$82,MATCH(B10,'Sales Data'!$B$2:$B$82,0)) -> North
A11: 8 | B11: =INDEX('Customer Summary'!$A$4:$A$18,MATCH(C11,'Customer Summary'!$B$4:$B$18,0)) -> Neha Verma | C11: =LARGE('Customer Summary'!$B$4:$B$18,A11) -> 7754.134 | D11: =INDEX('Sales Data'!$C$2:$C$82,MATCH(B11,'Sales Data'!$B$2:$B$82,0)) -> North
A12: 9 | B12: =INDEX('Customer Summary'!$A$4:$A$18,MATCH(C12,'Customer Summary'!$B$4:$B$18,0)) -> Pooja Joshi | C12: =LARGE('Customer Summary'!$B$4:$B$18,A12) -> 7689.26 | D12: =INDEX('Sales Data'!$C$2:$C$82,MATCH(B12,'Sales Data'!$B$2:$B$82,0)) -> North
A13: 10 | B13: =INDEX('Customer Summary'!$A$4:$A$18,MATCH(C13,'Customer Summary'!$B$4:$B$18,0)) -> Karan Malhotra | C13: =LARGE('Customer Summary'!$B$4:$B$18,A13) -> 5937.902 | D13: =INDEX('Sales Data'!$C$2:$C$82,MATCH(B13,'Sales Data'!$B$2:$B$82,0)) -> North
A16: Filter check: customers above overall average purchase
A17: Average Purchase per Customer | B17: =AVERAGE('Customer Summary'!$B$4:$B$18) -> 8059.6005
A18: Count of Customers Above Average | B18: =COUNTIF('Customer Summary'!$B$4:$B$18,">"&B17) -> 7

Sheet Pivot Summary
A1: PIVOT TABLE: TOTAL SALES BY REGION AND PRODUCT
A2: (Cross-tab summary built with SUMIFS — equivalent to Insert > PivotTable, Rows=Region, Columns=Product, Values=Sum of Sales)
A4: Region | B4: Product A | C4: Product B | D4: Product C | E4: Product D | F4: Grand Total
A5: North | B5: =SUMIFS('Sales Data'!$J$2:$J$82,'Sales Data'!$C$2:$C$82,$A5,'Sales Data'!$D$2:$D$82,B$4) -> 11091.323 | C5: =SUMIFS('Sales Data'!$J$2:$J$82,'Sales Data'!$C$2:$C$82,$A5,'Sales Data'!$D$2:$D$82,C$4) -> 13627.734 | D5: =SUMIFS('Sales Data'!$J$2:$J$82,'Sales Data'!$C$2:$C$82,$A5,'Sales Data'!$D$2:$D$82,D$4) -> 7238.466 | E5: =SUMIFS('Sales Data'!$J$2:$J$82,'Sales Data'!$C$2:$C$82,$A5,'Sales Data'!$D$2:$D$82,E$4) -> 11007.005 | F5: =SUM(B5:E5) -> 42964.528
A6: South | B6: =SUMIFS('Sales Data'!$J$2:$J$82,'Sales Data'!$C$2:$C$82,$A6,'Sales Data'!$D$2:$D$82,B$4) -> 12813.424 | C6: =SUMIFS('Sales Data'!$J$2:$J$82,'Sales Data'!$C$2:$C$82,$A6,'Sales Data'!$D$2:$D$82,C$4) -> 21800.346 | D6: =SUMIFS('Sales Data'!$J$2:$J$82,'Sales Data'!$C$2:$C$82,$A6,'Sales Data'!$D$2:$D$82,D$4) -> 4658.956 | E6: =SUMIFS('Sales Data'!$J$2:$J$82,'Sales Data'!$C$2:$C$82,$A6,'Sales Data'!$D$2:$D$82,E$4) -> 14577.027 | F6: =SUM(B6:E6) -> 53849.753
A7: East | B7: =SUMIFS('Sales Data'!$J$2:$J$82,'Sales Data'!$C$2:$C$82,$A7,'Sales Data'!$D$2:$D$82,B$4) -> 0 | C7: =SUMIFS('Sales Data'!$J$2:$J$82,'Sales Data'!$C$2:$C$82,$A7,'Sales Data'!$D$2:$D$82,C$4) -> 4884.255 | D7: =SUMIFS('Sales Data'!$J$2:$J$82,'Sales Data'!$C$2:$C$82,$A7,'Sales Data'!$D$2:$D$82,D$4) -> 0 | E7: =SUMIFS('Sales Data'!$J$2:$J$82,'Sales Data'!$C$2:$C$82,$A7,'Sales Data'!$D$2:$D$82,E$4) -> 8337.211 | F7: =SUM(B7:E7) -> 13221.466
A8: West | B8: =SUMIFS('Sales Data'!$J$2:$J$82,'Sales Data'!$C$2:$C$82,$A8,'Sales Data'!$D$2:$D$82,B$4) -> 5884.316 | C8: =SUMIFS('Sales Data'!$J$2:$J$82,'Sales Data'!$C$2:$C$82,$A8,'Sales Data'!$D$2:$D$82,C$4) -> 4315.864 | D8: =SUMIFS('Sales Data'!$J$2:$J$82,'Sales Data'!$C$2:$C$82,$A8,'Sales Data'!$D$2:$D$82,D$4) -> 658.08 | E8: =SUMIFS('Sales Data'!$J$2:$J$82,'Sales Data'!$C$2:$C$82,$A8,'Sales Data'!$D$2:$D$82,E$4) -> 0 | F8: =SUM(B8:E8) -> 10858.26
A9: Grand Total | B9: =SUM(B5:B8) -> 29789.063 | C9: =SUM(C5:C8) -> 44628.199 | D9: =SUM(D5:D8) -> 12555.502 | E9: =SUM(E5:E8) -> 33921.243 | F9: =SUM(F5:F8) -> 120894.01

Sheet Charts
A1: KPI VISUALIZATIONS
