Workbook

Sheet Dashboard
A1: EXECUTIVE DATA INTELLIGENCE DASHBOARD
A2: Performance Summary, KPI Indicators & Visualizations (Linked to Pivot Tables)
A4: Total Revenue | C4: Total Transactions | E4: Units Sold | G4: Average Order Value
A5: =SUM('Final Project Dataset'!J2:J221) | C5: =COUNTA('Final Project Dataset'!A2:A221) | E5: =SUM('Final Project Dataset'!G2:G221) | G5: =AVERAGE('Final Project Dataset'!J2:J221)
A6: Overall Sales | C6: Completed Orders | E6: Total Quantity | G6: Per Transaction

Sheet Final Project Dataset
A1: Transaction ID | B1: Customer ID | C1: Customer Name | D1: Region | E1: Product Name | F1: Category | G1: Quantity | H1: Unit Price | I1: Discount % | J1: Total Amount | K1: Transaction Date | L1: Status
A2: TXN-2001 | B2: CUST-202 | C2: Neha Deshmukh | D2: East | E2: Ultra HD Monitor | F2: Electronics | G2: 1 | H2: 350 | I2: 0 | J2: 350 | K2: 2026-08-19 | L2: Completed
A3: TXN-2002 | B3: CUST-203 | C3: Vivaan Sharma | D3: South | E3: Wireless Mouse | F3: Accessories | G3: 1 | H3: 25 | I3: 0 | J3: 25 | K3: 2025-08-13 | L3: Completed
A4: TXN-2003 | B4: CUST-204 | C4: Arjun Sharma | D4: Central | E4: Laptop Pro | F4: Electronics | G4: 2 | H4: 1200 | I4: 0 | J4: 2400 | K4: 2025-01-03 | L4: Completed
A5: TXN-2004 | B5: CUST-205 | C5: Amit Singh | D5: Central | E5: Noise-Canceling Headphones | F5: Audio | G5: 3 | H5: 180 | I5: 0.05 | J5: 513 | K5: 2026-01-16 | L5: Completed
A6: TXN-2005 | B6: CUST-206 | C6: Vivaan Shah | D6: North | E6: External SSD 1TB | F6: Storage | G6: 1 | H6: 130 | I6: 0 | J6: 130 | K6: 2026-08-12 | L6: Pending
A7: TXN-2006 | B7: CUST-207 | C7: Sai Sharma | D7: Central | E7: Ergonomic Keyboard | F7: Accessories | G7: 1 | H7: 75 | I7: 0 | J7: 75 | K7: 2025-05-27 | L7: Shipped
A8: TXN-2007 | B8: CUST-208 | C8: Priya Deshmukh | D8: Central | E8: USB-C Hub | F8: Accessories | G8: 2 | H8: 45 | I8: 0.05 | J8: 85.5 | K8: 2026-01-26 | L8: Completed
A9: TXN-2008 | B9: CUST-209 | C9: Reyansh Verma | D9: Central | E9: Ergonomic Keyboard | F9: Accessories | G9: 1 | H9: 75 | I9: 0 | J9: 75 | K9: 2026-03-11 | L9: Pending
A10: TXN-2009 | B10: CUST-210 | C10: Priya Gupta | D10: North | E10: Wireless Mouse | F10: Accessories | G10: 2 | H10: 25 | I10: 0 | J10: 50 | K10: 2025-11-01 | L10: Completed
A11: TXN-2010 | B11: CUST-211 | C11: Vihaan Patel | D11: West | E11: Ergonomic Keyboard | F11: Accessories | G11: 1 | H11: 75 | I11: 0 | J11: 75 | K11: 2025-12-21 | L11: Pending
A12: TXN-2011 | B12: CUST-212 | C12: Karan Singh | D12: South | E12: External SSD 1TB | F12: Storage | G12: 3 | H12: 130 | I12: 0 | J12: 390 | K12: 2026-04-13 | L12: Completed
A13: TXN-2012 | B13: CUST-213 | C13: Ayaan Verma | D13: South | E13: Noise-Canceling Headphones | F13: Audio | G13: 3 | H13: 180 | I13: 0.05 | J13: 513 | K13: 2025-04-10 | L13: Completed
... A221: TXN-2220 | B221: CUST-241 | C221: Neha Mehta | D221: South | E221: External SSD 1TB | F221: Storage | G221: 4 | H221: 130 | I221: 0 | J221: 520 | K221: 2025-03-26 | L221: Shipped

Sheet Pivot Tables
A1: DATA INTELLIGENCE - PIVOT TABLES & SUMMARY REPORTS
A3: Pivot Table 1: Regional Performance & Sales Summary
A4: Region | B4: Transaction Count | C4: Total Quantity | D4: Total Revenue ($) | E4: Average Order Value ($)
A5: Central | B5: =COUNTIF('Final Project Dataset'!$D$2:$D$221, A5) | C5: =SUMIF('Final Project Dataset'!$D$2:$D$221, A5, 'Final Project Dataset'!$G$2:$G$221) | D5: =SUMIF('Final Project Dataset'!$D$2:$D$221, A5, 'Final Project Dataset'!$J$2:$J$221) | E5: =D5/B5
A6: East | B6: =COUNTIF('Final Project Dataset'!$D$2:$D$221, A6) | C6: =SUMIF('Final Project Dataset'!$D$2:$D$221, A6, 'Final Project Dataset'!$G$2:$G$221) | D6: =SUMIF('Final Project Dataset'!$D$2:$D$221, A6, 'Final Project Dataset'!$J$2:$J$221) | E6: =D6/B6
A7: North | B7: =COUNTIF('Final Project Dataset'!$D$2:$D$221, A7) | C7: =SUMIF('Final Project Dataset'!$D$2:$D$221, A7, 'Final Project Dataset'!$G$2:$G$221) | D7: =SUMIF('Final Project Dataset'!$D$2:$D$221, A7, 'Final Project Dataset'!$J$2:$J$221) | E7: =D7/B7
A8: South | B8: =COUNTIF('Final Project Dataset'!$D$2:$D$221, A8) | C8: =SUMIF('Final Project Dataset'!$D$2:$D$221, A8, 'Final Project Dataset'!$G$2:$G$221) | D8: =SUMIF('Final Project Dataset'!$D$2:$D$221, A8, 'Final Project Dataset'!$J$2:$J$221) | E8: =D8/B8
A9: West | B9: =COUNTIF('Final Project Dataset'!$D$2:$D$221, A9) | C9: =SUMIF('Final Project Dataset'!$D$2:$D$221, A9, 'Final Project Dataset'!$G$2:$G$221) | D9: =SUMIF('Final Project Dataset'!$D$2:$D$221, A9, 'Final Project Dataset'!$J$2:$J$221) | E9: =D9/B9
A10: Grand Total | B10: =SUM(B5:B9) | C10: =SUM(C5:C9) | D10: =SUM(D5:D9) | E10: =AVERAGE(E5:E9)
A12: Pivot Table 2: Product Category Performance
A13: Product Name | B13: Category | C13: Units Sold | D13: Total Revenue ($) | E13: Revenue Share %
A14: Ergonomic Keyboard | B14: Accessories | C14: =SUMIF('Final Project Dataset'!$E$2:$E$221, A14, 'Final Project Dataset'!$G$2:$G$221) | D14: =SUMIF('Final Project Dataset'!$E$2:$E$221, A14, 'Final Project Dataset'!$J$2:$J$221) | E14: =D14/D10
A15: External SSD 1TB | B15: Storage | C15: =SUMIF('Final Project Dataset'!$E$2:$E$221, A15, 'Final Project Dataset'!$G$2:$G$221) | D15: =SUMIF('Final Project Dataset'!$E$2:$E$221, A15, 'Final Project Dataset'!$J$2:$J$221) | E15: =D15/D10
A16: Laptop Pro | B16: Electronics | C16: =SUMIF('Final Project Dataset'!$E$2:$E$221, A16, 'Final Project Dataset'!$G$2:$G$221) | D16: =SUMIF('Final Project Dataset'!$E$2:$E$221, A16, 'Final Project Dataset'!$J$2:$J$221) | E16: =D16/D10
A17: Noise-Canceling Headphones | B17: Audio | C17: =SUMIF('Final Project Dataset'!$E$2:$E$221, A17, 'Final Project Dataset'!$G$2:$G$221) | D17: =SUMIF('Final Project Dataset'!$E$2:$E$221, A17, 'Final Project Dataset'!$J$2:$J$221) | E17: =D17/D10
A18: Smart Tablet | B18: Electronics | C18: =SUMIF('Final Project Dataset'!$E$2:$E$221, A18, 'Final Project Dataset'!$G$2:$G$221) | D18: =SUMIF('Final Project Dataset'!$E$2:$E$221, A18, 'Final Project Dataset'!$J$2:$J$221) | E18: =D18/D10
A19: USB-C Hub | B19: Accessories | C19: =SUMIF('Final Project Dataset'!$E$2:$E$221, A19, 'Final Project Dataset'!$G$2:$G$221) | D19: =SUMIF('Final Project Dataset'!$E$2:$E$221, A19, 'Final Project Dataset'!$J$2:$J$221) | E19: =D19/D10
A20: Ultra HD Monitor | B20: Electronics | C20: =SUMIF('Final Project Dataset'!$E$2:$E$221, A20, 'Final Project Dataset'!$G$2:$G$221) | D20: =SUMIF('Final Project Dataset'!$E$2:$E$221, A20, 'Final Project Dataset'!$J$2:$J$221) | E20: =D20/D10
A21: Wireless Mouse | B21: Accessories | C21: =SUMIF('Final Project Dataset'!$E$2:$E$221, A21, 'Final Project Dataset'!$G$2:$G$221) | D21: =SUMIF('Final Project Dataset'!$E$2:$E$221, A21, 'Final Project Dataset'!$J$2:$J$221) | E21: =D21/D10
A22: Grand Total | C22: =SUM(C14:C21) | D22: =SUM(D14:D21) | E22: =SUM(E14:E21)

Sheet Analysis & Formulas
A1: ADVANCED ANALYSIS, FORMULAS & BUSINESS RULES IMPLEMENTATION
A3: 1. Date & Time Functions (TODAY, NOW, DATEDIF, EOMONTH)
A4: Function Name | B4: Excel Formula | C4: Description / Result
A5: TODAY() | B5: =TODAY() | C5: Returns current system date
A6: NOW() | B6: =NOW() | C6: Returns current timestamp (Date & Time)
A7: DATEDIF() | B7: =DATEDIF(MIN('Final Project Dataset'!K2:K221), MAX('Final Project Dataset'!K2:K221), "d") | C7: Total days span of project dataset transactions
A8: EOMONTH() | B8: =EOMONTH(TODAY(), 0) | C8: Calculates the last day of the current month
A11: 2. FILTER Function & GroupBy High-Value Customers
A12: Analysis Requirement | B12: Formula / Implementation | C12: Purpose
A13: FILTER Function | B13: =FILTER('Final Project Dataset'!A2:L221, 'Final Project Dataset'!D2:D221="North") | C13: Extracts multi-value records dynamically for North region
A14: GroupBy High-Value Customer | B14: =SUMIF('Final Project Dataset'!$C$2:$C$221, C2, 'Final Project Dataset'!$J$2:$J$221) | C14: Aggregates total customer spend to identify VIP accounts
A15: Most Frequent Product | B15: =INDEX('Final Project Dataset'!$E$2:$E$221, MODE(MATCH('Final Project Dataset'!$E$2:$E$221, 'Final Project Dataset'!$E$2:$E$221, 0))) | C15: Finds most frequently purchased product
A18: 3. What-If Analysis & Scenario Manager
A19: Scenario Name | B19: Discount Adjustment Rate | C19: Projected Total Revenue ($) | D19: Variance vs Baseline ($)
A20: Baseline Scenario | B20: 0.08 | C20: =SUM('Final Project Dataset'!J2:J221) | D20: 0
A21: Optimistic Scenario (Lower Discounts) | B21: 0.03 | C21: =SUM('Final Project Dataset'!J2:J221)*1.05 | D21: =C21-C20
A22: Conservative Scenario (Higher Discounts) | B22: 0.12 | C22: =SUM('Final Project Dataset'!J2:J221)*0.95 | D22: =C22-C20
A25: 4. Text Functions & Abbreviations
A26: Text Operation | B26: Formula Used | C26: Result Example
A27: Customer Abbreviation | B27: =UPPER(LEFT(C2, 3)) & "-" & TEXT(ROW(C2), "000") | C27: RAH-002
A28: List Matching (XLOOKUP / MATCH) | B28: =XLOOKUP("Laptop Pro", 'Final Project Dataset'!$E$2:$E$221, 'Final Project Dataset'!$J$2:$J$221) | C28: Extracts matching transaction amount
A29: Linear Regression (Toolpak) | B29: Data Analysis > Regression Toolpak | C29: Predicts sales trend over time periods
